eniius/__init__.py
eniius/_version.py
eniius/eniius.py
eniius/horace.py
eniius/mcstas.py
eniius/nexus.py
eniius/writer.py
eniius/instruments/README.md
eniius/instruments/detector.dat
eniius/instruments/horace_let_tables.mat
eniius/instruments/isis_let.instr
eniius/instruments/isis_maps.instr
eniius/instruments/isis_mari.instr
eniius/instruments/isis_merlin.instr
eniius/mcstas-comps/contrib/Al_window.comp
eniius/mcstas-comps/contrib/CavitiesIn.comp
eniius/mcstas-comps/contrib/CavitiesOut.comp
eniius/mcstas-comps/contrib/Collimator_ROC.comp
eniius/mcstas-comps/contrib/Conics_EH.comp
eniius/mcstas-comps/contrib/Conics_HE.comp
eniius/mcstas-comps/contrib/Conics_PH.comp
eniius/mcstas-comps/contrib/Conics_PP.comp
eniius/mcstas-comps/contrib/E_4PI.comp
eniius/mcstas-comps/contrib/Exact_radial_coll.comp
eniius/mcstas-comps/contrib/FermiChopper_ILL.comp
eniius/mcstas-comps/contrib/Fermi_chop2a.comp
eniius/mcstas-comps/contrib/Filter_graphite.comp
eniius/mcstas-comps/contrib/FlatEllipse_finite_mirror.comp
eniius/mcstas-comps/contrib/Foil_flipper_magnet.comp
eniius/mcstas-comps/contrib/GISANS_sample.comp
eniius/mcstas-comps/contrib/Guide_anyshape_r.comp
eniius/mcstas-comps/contrib/Guide_curved.comp
eniius/mcstas-comps/contrib/Guide_four_side.comp
eniius/mcstas-comps/contrib/Guide_gravity_psd.comp
eniius/mcstas-comps/contrib/Guide_honeycomb.comp
eniius/mcstas-comps/contrib/Guide_m.comp
eniius/mcstas-comps/contrib/Guide_multichannel.comp
eniius/mcstas-comps/contrib/ISIS_moderator.comp
eniius/mcstas-comps/contrib/Lens.comp
eniius/mcstas-comps/contrib/Lens_simple.comp
eniius/mcstas-comps/contrib/Mirror_Curved_Bispectral.comp
eniius/mcstas-comps/contrib/Mirror_Elliptic.comp
eniius/mcstas-comps/contrib/Mirror_Elliptic_Bispectral.comp
eniius/mcstas-comps/contrib/Mirror_Parabolic.comp
eniius/mcstas-comps/contrib/Monochromator_2foc.comp
eniius/mcstas-comps/contrib/Monochromator_bent.comp
eniius/mcstas-comps/contrib/MultiDiskChopper.comp
eniius-0.2.0.dist-info/LICENSE
eniius-0.2.0.dist-info/METADATA
eniius-0.2.0.dist-info/WHEEL
eniius-0.2.0.dist-info/top_level.txt
eniius-0.2.0.dist-info/RECORD
