Metadata-Version: 2.1
Name: eniius
Version: 0.2.0
Summary: A utility for embedding neutron instrument information using (nx)spe files.
Home-page: https://github.com/mducle/eniius
Author: Duc Le
Author-email: duc.le@stfc.ac.uk
License: UNKNOWN
Platform: UNKNOWN
Classifier: Development Status :: 2 - Pre-Alpha
Classifier: Intended Audience :: Science/Research
Classifier: License :: OSI Approved :: MIT License
Classifier: Operating System :: Microsoft :: Windows :: Windows 10
Classifier: Operating System :: POSIX :: Linux
Classifier: Programming Language :: Python :: 3
Classifier: Topic :: Scientific/Engineering :: Physics
License-File: LICENSE
Requires-Dist: mcstasscript (>=0.0.54)
Requires-Dist: nexusformat (>=0.7.8)
Requires-Dist: regex
